{"nombre":"Yelsin Ercilia Sandoval","num":"1111","pass":"yelsin"}
{"nombre":"Raul Palma","num":"4444","pass":"raul"}
{"nombre":"Hector Guevara","num":"1414","pass":"hector"}
{"nombre":"Hermes Paul Bautista","num":"2525","pass":"hermes"}
{"nombre":"Luis Dominguez","num":"7878","pass":"luis"}
{"nombre":"Abdiel Salomon Sevilla","num":"8989","pass":"abdiel"}
{"nombre":"Luis Sanchez","num":"3333","pass":"sanchez"}
{"nombre":"Erick Vladimir Marin","num":"1515","pass":"asd"}
{"nombre":"Arias Lopez","num":"0801","pass":"arias"}
{"nombre":"Paola Gomez","num":"0901","pass":"paola"}
{"nombre":"Marco Moncada","num":"1021","pass":"marco"}
{"nombre":"David Corea","num":"9045","pass":"david"}
{"nombre":"Fernando Fiallo","num":"4563","pass":"fernando"}
{"nombre":"David Zuniga","num":"7845","pass":"david"}
{"nombre":"Oscar Hernandez","num":"6912","pass":"oscar"}
{"nombre":"Servio zuniga","num":"9871","pass":"servio"}
{"nombre":"Lorenzo Guevara","num":"4587","pass":"lorenzo"}
{"nombre":"Julio Cesar","num":"0314","pass":"julio"}
{"nombre":"Jair noel","num":"7852","pass":"jair"}
{"nombre":"Marlon Mejilla","num":"9317","pass":"marlon"}
{"nombre":"Pamela Cruz","num":"5553","pass":"pamela"}
{"nombre":"Alejandra Cruz","num":"3345","pass":"alejandra"}
{"nombre":"Carlos Sosa","num":"7891","pass":"carlos"}
{"nombre":"Luis Dominguez","num":"7797","pass":"luis"}
{"nombre":"Hector Cordova","num":"3184","pass":"hector"}
{"nombre":"Orlando Fortin","num":"7413","pass":"orlando"}
{"nombre":"Josue Mendez","num":"4718","pass":"josue"}
{"nombre":"Lizeth Sierra","num":"7888","pass":"lizeth"}
{"nombre":"Maria Sauceda","num":"9856","pass":"maria"}
{"nombre":"Hilda Carranza","num":"1994","pass":"hilda"}
